landuse-rb/__init__.py
landuse-rb/classification.py
landuse-rb/model.py
landuse-rb/visualization.py
landuse_rb/__init__.py
landuse_rb/classification.py
landuse_rb/model.py
landuse_rb/visualization.py
landuse_rb-0.0.1.dist-info/licenses/LICENSE
landuse_rb-0.0.1.dist-info/METADATA
landuse_rb-0.0.1.dist-info/WHEEL
landuse_rb-0.0.1.dist-info/top_level.txt
landuse_rb-0.0.1.dist-info/RECORD
