Metadata-Version: 2.4
Name: landuse_rb
Version: 0.0.1
Summary: A library for land use classification and spatial analysis
Home-page: https://github.com/romanroff/landuse-lib
Author: Roman Bashirov
Author-email: Roman Bashirov <bashiroff.roman@gmail.com>
License: MIT
Project-URL: Homepage, https://github.com/romanroff/landuse-lib
Project-URL: Repository, https://github.com/romanroff/landuse-lib
Requires-Python: >=3.10
License-File: LICENSE
Requires-Dist: pandas
Requires-Dist: geopandas
Requires-Dist: scikit-learn
Requires-Dist: xgboost
Requires-Dist: lightgbm
Requires-Dist: catboost
Requires-Dist: matplotlib
Requires-Dist: imbalanced-learn
Requires-Dist: libpysal
Dynamic: author
Dynamic: home-page
Dynamic: license-file
Dynamic: requires-python
